{
  "resourceType" : "Condition",
  "id" : "condition-2",
  "clinicalStatus" : {
    "coding" : [{
      "system" : "http://terminology.hl7.org/CodeSystem/condition-clinical",
      "code" : "active"
    }]
  },
  "verificationStatus" : {
    "coding" : [{
      "system" : "http://terminology.hl7.org/CodeSystem/condition-ver-status",
      "code" : "confirmed"
    }]
  },
  "category" : [
    {
        "coding" : [{
        "system" : "http://snomed.info/sct",
        "code" : "439401001",
        "display" : "Diagnosis"
      }]
    }
  ],
  "severity" : {
    "coding" : [{
      "system" : "http://snomed.info/sct",
      "code" : "1255665007",
      "display" : "Moderate"
    }]
  },
  "code" : {
    "coding" : [{
      "system" : "http://id.who.int/icd/release/11/mms",
      "code" : "6D85.7&XS0T/NA07",
      "display" : "Dementia due to injury to the head [Moderate] [Intracranial injury]"
    }],
    "text" : "Moderate dementia subsequent to head injury"
  },
  "subject" : {
    "reference" : "Patient/example"
  },
  "onsetDateTime" : "2012-05-24"
}